qcentroid_agent_cli/__init__.py
qcentroid_agent_cli/model/__init__.py
qcentroid_agent_cli-0.3.38.dist-info/LICENSE
qcentroid_agent_cli-0.3.38.dist-info/METADATA
qcentroid_agent_cli-0.3.38.dist-info/WHEEL
qcentroid_agent_cli-0.3.38.dist-info/RECORD
