Metadata-Version: 2.1
Name: qcentroid-agent-cli
Version: 0.3.38
Summary: Library to interact with qcentroid agent api
Home-page: https://www.qcentroid.xyz
License: MIT
Author: QCentroid
Author-email: info@qcentroid.xyz
Requires-Python: >=3.8,<4.0
Classifier: License :: OSI Approved :: MIT License
Classifier: Operating System :: OS Independent
Classifier: Programming Language :: Python :: 3
Classifier: Programming Language :: Python :: 3.8
Classifier: Programming Language :: Python :: 3.9
Classifier: Programming Language :: Python :: 3.10
Classifier: Programming Language :: Python :: 3.11
Classifier: Programming Language :: Python :: 3.12
Provides-Extra: test
Requires-Dist: pytest (>=7.4,<7.5) ; extra == "test"
Requires-Dist: requests (>=2.32,<3.0)
Requires-Dist: requests_toolbelt (>=1.0,<2.0)
Requires-Dist: responses (>=0.25,<1.0) ; extra == "test"
Project-URL: Documentation, https://github.com/QCentroid/qcentroid-agent-cli
Project-URL: Repository, https://github.com/QCentroid/qcentroid-agent-cli
